proof_of_portfolio/__init__.py
proof_of_portfolio/_version.py
proof_of_portfolio/analyze_data.py
proof_of_portfolio/main.py
proof_of_portfolio/miner.py
proof_of_portfolio/parsing_utils.py
proof_of_portfolio/post_install.py
proof_of_portfolio/proof_fetcher.py
proof_of_portfolio/proof_generator.py
proof_of_portfolio/signal_processor.py
proof_of_portfolio/validator.py
proof_of_portfolio/verifier.py
proof_of_portfolio/circuits/Nargo.toml
proof_of_portfolio/circuits/generate_inputs.py
proof_of_portfolio/circuits/components/Nargo.toml
proof_of_portfolio/circuits/components/src/lib.nr
proof_of_portfolio/circuits/components/src/core/calmar.nr
proof_of_portfolio/circuits/components/src/core/drawdown.nr
proof_of_portfolio/circuits/components/src/core/merkle.nr
proof_of_portfolio/circuits/components/src/core/mod.nr
proof_of_portfolio/circuits/components/src/core/omega.nr
proof_of_portfolio/circuits/components/src/core/sharpe.nr
proof_of_portfolio/circuits/components/src/core/sortino.nr
proof_of_portfolio/circuits/components/src/core/tstat.nr
proof_of_portfolio/circuits/components/src/utils/ann_excess_return.nr
proof_of_portfolio/circuits/components/src/utils/ann_volatility.nr
proof_of_portfolio/circuits/components/src/utils/average.nr
proof_of_portfolio/circuits/components/src/utils/constants.nr
proof_of_portfolio/circuits/components/src/utils/downside_variance.nr
proof_of_portfolio/circuits/components/src/utils/mod.nr
proof_of_portfolio/circuits/components/src/utils/risk_normalization.nr
proof_of_portfolio/circuits/components/src/utils/sqrt.nr
proof_of_portfolio/circuits/components/src/utils/variance.nr
proof_of_portfolio/circuits/components/src/utils/weighting_distribution.nr
proof_of_portfolio/circuits/src/main.nr
proof_of_portfolio/circuits/target/circuits.json
proof_of_portfolio/circuits/vk/vk
proof_of_portfolio/circuits/vk/vk_hash
proof_of_portfolio/circuits/vk_new/vk/vk
proof_of_portfolio/demos/generate_input_data.py
proof_of_portfolio/demos/main.py
proof_of_portfolio-0.0.172.dist-info/METADATA
proof_of_portfolio-0.0.172.dist-info/WHEEL
proof_of_portfolio-0.0.172.dist-info/entry_points.txt
proof_of_portfolio-0.0.172.dist-info/top_level.txt
proof_of_portfolio-0.0.172.dist-info/RECORD
