Metadata-Version: 2.4
Name: proof-of-portfolio
Version: 0.0.172
Summary: Zero-Knowledge Proof framework for verifiable, private portfolio performance metrics
Author-email: "Inference Labs, Inc." <info@inferencelabs.com>
Requires-Python: >=3.10
Requires-Dist: numpy
Requires-Dist: colorama
Requires-Dist: matplotlib
Requires-Dist: toml
Requires-Dist: scipy
Requires-Dist: bittensor
Requires-Dist: setproctitle>=1.3.7
Provides-Extra: dev
Requires-Dist: black; extra == "dev"
Requires-Dist: flake8; extra == "dev"
Requires-Dist: pre-commit; extra == "dev"
